pisces/__init__.py
pisces/client.py
pisces/crud.py
pisces/events.py
pisces/inventory.py
pisces/request.py
pisces/stations.py
pisces/util.py
pisces/commands/__init__.py
pisces/commands/create.py
pisces/commands/db2db.py
pisces/commands/drop.py
pisces/commands/main.py
pisces/commands/mseed2db.py
pisces/commands/sac2db.py
pisces/commands/util.py
pisces/io/__init__.py
pisces/io/mseed.py
pisces/io/readwaveform.py
pisces/io/response.py
pisces/io/sac.py
pisces/io/trace.py
pisces/io/util.py
pisces/schema/__init__.py
pisces/schema/antelope.py
pisces/schema/css3.py
pisces/schema/kbcore.py
pisces/schema/util.py
pisces/tables/__init__.py
pisces/tables/antelope.py
pisces/tables/css3.py
pisces/tables/kbcore.py
pisces-0.4.5.dist-info/licenses/AUTHORS.rst
pisces-0.4.5.dist-info/licenses/LICENSE.txt
pisces-0.4.5.dist-info/METADATA
pisces-0.4.5.dist-info/WHEEL
pisces-0.4.5.dist-info/entry_points.txt
pisces-0.4.5.dist-info/top_level.txt
pisces-0.4.5.dist-info/RECORD
