Metadata-Version: 2.4
Name: pisces
Version: 0.4.5
Summary: A Practical Seismological Database Library in Python.
Home-page: https://github.com/LANL-Seismoacoustics/pisces
Download-URL: https://github.com/LANL-Seismoacoustics/pisces/tarball/0.4.2
Author: Jonathan MacCarthy
Author-email: jkmacc@lanl.gov
License: LANL-MIT
Keywords: seismology,geophysics,database
Platform: Mac OS X
Platform: Linux/Unix
Classifier: Development Status :: 3 - Alpha
Classifier: Environment :: Console
Classifier: Intended Audience :: Science/Research
Classifier: Intended Audience :: Developers
Classifier: License :: OSI Approved :: MIT License
Classifier: Operating System :: OS Independent
Classifier: Programming Language :: Python :: 3
Classifier: Topic :: Scientific/Engineering
Classifier: Topic :: Database
Classifier: Topic :: Scientific/Engineering :: Physics
License-File: LICENSE.txt
License-File: AUTHORS.rst
Requires-Dist: numpy
Requires-Dist: obspy>=1.4.1
Requires-Dist: sqlalchemy>=1.4
Requires-Dist: Click
Provides-Extra: e1
Requires-Dist: e1; extra == "e1"
Dynamic: author
Dynamic: author-email
Dynamic: classifier
Dynamic: description
Dynamic: description-content-type
Dynamic: download-url
Dynamic: home-page
Dynamic: keywords
Dynamic: license
Dynamic: license-file
Dynamic: platform
Dynamic: provides-extra
Dynamic: requires-dist
Dynamic: summary
